lemonsync
