Metadata-Version: 1.1
Name: lemonsync
Version: 0.1.15
Summary: LemonSync will listen for changes in the folder you configure, and automatically push updates to your store theme.
Home-page: http://pypi.python.org/lemonstand/lemonsync
Author: LemonStand
Author-email: chris@lemonstand.com
License: MIT
Download-URL: https://github.com/lemonstand/lemonsync
Platform: Posix; MacOS X; Windows
Classifier: Development Status :: 4 - Beta
Classifier: Intended Audience :: Developers
Classifier: License :: OSI Approved :: MIT License
Classifier: Operating System :: OS Independent
Classifier: Topic :: Internet
Classifier: Programming Language :: Python :: 2.7
